_dcdftbmd_tools_cpp_extension_md.cpython-37m-x86_64-linux-gnu.so
dcdftbmd_tools/__init__.py
dcdftbmd_tools/io/output_parser.py
dcdftbmd_tools/io/translate_xyz.py
dcdftbmd_tools/io/__init__.py
dcdftbmd_tools/io/md_merger.py
dcdftbmd_tools/analysis/md_msd.py
dcdftbmd_tools/analysis/md_stats.py
dcdftbmd_tools/analysis/md_msd_fit.py
dcdftbmd_tools/analysis/__init__.py
dcdftbmd_tools/analysis/rdf.py
dcdftbmd_tools-0.1.2.dist-info/top_level.txt
dcdftbmd_tools-0.1.2.dist-info/RECORD
dcdftbmd_tools-0.1.2.dist-info/METADATA
dcdftbmd_tools-0.1.2.dist-info/WHEEL
dcdftbmd_tools-0.1.2.data/scripts/metadynamics_tool.py
dcdftbmd_tools-0.1.2.data/scripts/dcdftbmd.md_msd
dcdftbmd_tools-0.1.2.data/scripts/dcdftbmd.make_supercell
dcdftbmd_tools-0.1.2.data/scripts/dcdftbmd.final_geometry
dcdftbmd_tools-0.1.2.data/scripts/dcdftbmd.md_merger
dcdftbmd_tools-0.1.2.data/scripts/dcdftbmd.rdf
dcdftbmd_tools-0.1.2.data/scripts/dcdftbmd.md_stats
dcdftbmd_tools-0.1.2.data/scripts/dcdftbmd.translate_xyz
dcdftbmd_tools-0.1.2.data/scripts/dcdftbmd.stride_xyz
