Metadata-Version: 2.1
Name: dcdftbmd-tools
Version: 0.1.2
Summary: A Toolkit for handling DCDFTBMD input/output
Home-page: https://github.com/solccp/dcdftbmd_tools
Author: Chien-Pin Chou
Author-email: sol.chou@gmail.com
License: UNKNOWN
Platform: UNKNOWN
Classifier: Programming Language :: Python :: 3
Classifier: Development Status :: 3 - Alpha
Classifier: License :: OSI Approved :: GNU Lesser General Public License v3 (LGPLv3)
Requires-Dist: pybind11 (>=2.2.4)
Requires-Dist: statsmodels (>=0.9.0)
Requires-Dist: matplotlib (>=3.0)
Requires-Dist: MDAnalysis (>=0.19)
Requires-Dist: pymatgen (>=2019.3.13)
Requires-Dist: PyQt5 (>=5.13)
Requires-Dist: scikit-learn (>=0.21)
Requires-Dist: pyqtgraph
Requires-Dist: pgcolorbar
